testnph_jun4/__init__.py
testnph_jun4/test123.py
testnph_jun4-0.0.5.dist-info/METADATA
testnph_jun4-0.0.5.dist-info/WHEEL
testnph_jun4-0.0.5.dist-info/top_level.txt
testnph_jun4-0.0.5.dist-info/RECORD
