Metadata-Version: 2.1
Name: testnph-jun4
Version: 0.0.5
Summary: A package for calculaor
Home-page: UNKNOWN
Author: nikhesh
Author-email: nikhesh1999@gmail.com
License: UNKNOWN
Platform: UNKNOWN
Classifier: Programming Language :: Python :: 3
Classifier: License :: Other/Proprietary License
Classifier: Operating System :: OS Independent
